metaflow_extensions/ray/plugins/constants.py
metaflow_extensions/ray/plugins/datastore.py
metaflow_extensions/ray/plugins/exceptions.py
metaflow_extensions/ray/plugins/mfextinit_ray.py
metaflow_extensions/ray/plugins/ray_decorator.py
metaflow_extensions/ray/plugins/ray_started_check.py
metaflow_extensions/ray/plugins/ray_utils.py
metaflow_extensions/ray/plugins/status_notifier.py
metaflow_ray-0.1.3.dist-info/LICENSE
metaflow_ray-0.1.3.dist-info/METADATA
metaflow_ray-0.1.3.dist-info/WHEEL
metaflow_ray-0.1.3.dist-info/top_level.txt
metaflow_ray-0.1.3.dist-info/RECORD
