Metadata-Version: 2.1
Name: metaflow-ray
Version: 0.1.3
Summary: An EXPERIMENTAL Ray decorator for Metaflow
Author: Riley Hun
Author-email: riley.hun@autodesk.com
License-File: LICENSE
